anta_database/__init__.py
anta_database/anta_database.py
anta_database/compiling/__init__.py
anta_database/compiling/compile.py
anta_database/compiling/reconnect.py
anta_database/data/ANT_Basins_IMBIE2_v1.6.cpg
anta_database/data/ANT_Basins_IMBIE2_v1.6.dbf
anta_database/data/ANT_Basins_IMBIE2_v1.6.prj
anta_database/data/ANT_Basins_IMBIE2_v1.6.shp
anta_database/data/ANT_Basins_IMBIE2_v1.6.shx
anta_database/data/GL.pkl
anta_database/data/centeroid_coords_basins.cpg
anta_database/data/centeroid_coords_basins.dbf
anta_database/data/centeroid_coords_basins.prj
anta_database/data/centeroid_coords_basins.shp
anta_database/data/centeroid_coords_basins.shx
anta_database/data/site-coords.pkl
anta_database/database/__init__.py
anta_database/database/database.py
anta_database/figures/AntA_38ka.png
anta_database/indexing/__init__.py
anta_database/indexing/index_database.py
anta_database/plotting/__init__.py
anta_database/plotting/plotting.py
anta_database-0.3.6.dist-info/licenses/LICENSE
anta_database-0.3.6.dist-info/METADATA
anta_database-0.3.6.dist-info/WHEEL
anta_database-0.3.6.dist-info/top_level.txt
anta_database-0.3.6.dist-info/RECORD
