Metadata-Version: 2.4
Name: anta_database
Version: 0.3.6
Summary: SQLite database for the AntArchitecture Community Data
Author: Antoine Hermant
Author-email: antoine.hermant@etik.com
License-Expression: MIT
Project-URL: Homepage, https://antoinehermant.github.io/anta_database/intro
Project-URL: Documentation, https://antoinehermant.github.io/anta_database/quick_start
Project-URL: Repository, https://github.com/antoinehermant/anta_database.git
Project-URL: Issues, https://github.com/antoinehermant/anta_database/issues
Keywords: isochrones,database,IRH,radar
Classifier: Development Status :: 4 - Beta
Classifier: Intended Audience :: Science/Research
Classifier: Topic :: Scientific/Engineering :: Physics
Classifier: Programming Language :: Python
Requires-Python: >=3.11
License-File: LICENSE
Requires-Dist: pandas
Requires-Dist: geopandas
Requires-Dist: xarray
Requires-Dist: h5netcdf
Requires-Dist: h5py
Requires-Dist: pyproj
Requires-Dist: scipy
Requires-Dist: matplotlib
Requires-Dist: colormaps
Requires-Dist: tqdm
Requires-Dist: pyshp
Dynamic: license-file
